dxfeed/__init__.py
dxfeed/core/__init__.py
dxfeed/core/DXFeed_64.dll
dxfeed/core/DXFeed_64.lib
dxfeed/core/DXFeedPy.pyx
dxfeed/core/listeners/__init__.py
dxfeed/core/listeners/listener.pxd
dxfeed/core/listeners/listener.pyx
dxfeed/core/pxd_include/__init__.py
dxfeed/core/pxd_include/DXErrorCodes.pxd
dxfeed/core/pxd_include/DXFeed.pxd
dxfeed/core/pxd_include/DXTypes.pxd
dxfeed/core/pxd_include/EventData.pxd
dxfeed/core/pxd_include/RecordData.pxd
dxfeed/core/utils/__init__.py
dxfeed/core/utils/data_class.py
dxfeed/core/utils/handler.pxd
dxfeed/core/utils/handler.pyx
dxfeed/core/utils/helpers.pxd
dxfeed/core/utils/helpers.pyx
dxfeed/dxfeed-c-api/include/DXErrorCodes.h
dxfeed/dxfeed-c-api/include/DXFeed.h
dxfeed/dxfeed-c-api/include/DXTypes.h
dxfeed/dxfeed-c-api/include/EventData.h
dxfeed/dxfeed-c-api/include/RecordData.h
dxfeed/wrappers/__init__.py
dxfeed/wrappers/class_utils.py
dxfeed/wrappers/endpoint.py
dxfeed/wrappers/subscription.py
LICENSE
dxfeed/__init__.py
dxfeed/core/DXFeedPy.c
dxfeed/core/DXFeedPy.cp38-win_amd64.pyd
dxfeed/core/DXFeedPy.pyx
dxfeed/core/DXFeed_64.dll
dxfeed/core/DXFeed_64.lib
dxfeed/core/__init__.py
dxfeed/core/listeners/listener.c
dxfeed/core/listeners/listener.cp38-win_amd64.pyd
dxfeed/core/listeners/listener.pxd
dxfeed/core/listeners/listener.pyx
dxfeed/core/listeners/__init__.py
dxfeed/core/pxd_include/DXErrorCodes.pxd
dxfeed/core/pxd_include/DXFeed.pxd
dxfeed/core/pxd_include/DXTypes.pxd
dxfeed/core/pxd_include/EventData.pxd
dxfeed/core/pxd_include/RecordData.pxd
dxfeed/core/pxd_include/__init__.py
dxfeed/core/utils/data_class.py
dxfeed/core/utils/handler.c
dxfeed/core/utils/handler.cp38-win_amd64.pyd
dxfeed/core/utils/handler.pxd
dxfeed/core/utils/handler.pyx
dxfeed/core/utils/helpers.c
dxfeed/core/utils/helpers.cp38-win_amd64.pyd
dxfeed/core/utils/helpers.pxd
dxfeed/core/utils/helpers.pyx
dxfeed/core/utils/__init__.py
dxfeed/dxfeed-c-api/include/DXErrorCodes.h
dxfeed/dxfeed-c-api/include/DXFeed.h
dxfeed/dxfeed-c-api/include/DXTypes.h
dxfeed-0.5.3.dist-info/LICENSE
dxfeed-0.5.3.dist-info/WHEEL
dxfeed-0.5.3.dist-info/METADATA
dxfeed-0.5.3.dist-info/RECORD
