Metadata-Version: 2.1
Name: dxfeed
Version: 0.5.3
Summary: DXFeed Python API via C API
License: MPL-2.0
Author: Index Management Team
Author-email: im@dxfeed.com
Requires-Python: >=3.6,<4.0
Classifier: Development Status :: 4 - Beta
Classifier: License :: OSI Approved
Classifier: License :: OSI Approved :: Mozilla Public License 2.0 (MPL 2.0)
Classifier: Natural Language :: English
Classifier: Operating System :: MacOS
Classifier: Operating System :: Microsoft :: Windows
Classifier: Operating System :: POSIX :: Linux
Classifier: Programming Language :: Cython
Classifier: Programming Language :: Python :: 3
Classifier: Programming Language :: Python :: 3 :: Only
Classifier: Programming Language :: Python :: 3.6
Classifier: Programming Language :: Python :: 3.7
Classifier: Programming Language :: Python :: 3.8
Classifier: Programming Language :: Python :: 3.9
Classifier: Topic :: Office/Business :: Financial
Provides-Extra: docs
Requires-Dist: cython (>=0.29.14,<0.30.0); extra == "docs"
Requires-Dist: jupyter (>=1.0.0,<2.0.0); extra == "docs"
Requires-Dist: pandas (>=1.0,!=1.1.5,<1.2); python_full_version >= "3.6.1" and python_version < "3.7"
Requires-Dist: pandas (>=1.0.0,<2.0.0); python_version >= "3.7" and python_version < "4.0"
Requires-Dist: toml (>=0.10.2,<0.11.0)
Project-URL: Documentation, https://dxfeed.readthedocs.io/en/latest/
Project-URL: Source code, https://github.com/dxFeed/dxfeed-python-api
